gamezone/__init__.py
gamezone/pong.py
gamezone/snake.py
gamezone-0.0.3.dist-info/METADATA
gamezone-0.0.3.dist-info/WHEEL
gamezone-0.0.3.dist-info/top_level.txt
gamezone-0.0.3.dist-info/RECORD
