Metadata-Version: 2.4
Name: gamezone
Version: 0.0.3
Summary: A collection of classic arcade games built with Python and Turtle Graphics.
Home-page: https://github.com/shreeya2424/pygamezone
Author: Shreeya Singh
Author-email: shreeyasingh2404@gmail.com
Classifier: Programming Language :: Python :: 3
Classifier: License :: OSI Approved :: MIT License
Classifier: Operating System :: OS Independent
Dynamic: author
Dynamic: author-email
Dynamic: classifier
Dynamic: description
Dynamic: description-content-type
Dynamic: home-page
Dynamic: summary
